Metadata-Version: 2.1
Name: bagcat
Version: 0.0.6
Summary: A command line utility for managing BagIt packages in Amazon S3
Home-page: https://github.com/umd-mith/bagcat/
Author: Ed Summers
Author-email: ehs@pobox.com
License: UNKNOWN
Platform: UNKNOWN
